transfer_learning_vision_classifiers/__about__.py
transfer_learning_vision_classifiers/__init__.py
transfer_learning_vision_classifiers/classifiers.py
transfer_learning_vision_classifiers-0.2.0.dist-info/METADATA
transfer_learning_vision_classifiers-0.2.0.dist-info/WHEEL
transfer_learning_vision_classifiers-0.2.0.dist-info/licenses/LICENSE
transfer_learning_vision_classifiers-0.2.0.dist-info/RECORD
