Metadata-Version: 2.1
Name: transfer_learning_vision_classifiers
Version: 0.2.0
Summary: A simple package for creating computer vision classifiers based on transfer learning.
Project-URL: Homepage, https://github.com/jme45/transfer_learning_vision_classifiers
Project-URL: Issues, https://github.com/jme45/transfer_learning_vision_classifiers/issues
Author-email: Jonathan Edge <j.edge@zoho.com>
License-File: LICENSE
Classifier: License :: OSI Approved :: MIT License
Classifier: Operating System :: OS Independent
Classifier: Programming Language :: Python :: 3
Requires-Python: >=3.8
